LICENSE
README.md
setup.py
wut/__init__.py
wut/__main__.py
wut/prompts.py
wut/utils.py
wut/wut.py
wut_cli.egg-info/PKG-INFO
wut_cli.egg-info/SOURCES.txt
wut_cli.egg-info/dependency_links.txt
wut_cli.egg-info/entry_points.txt
wut_cli.egg-info/requires.txt
wut_cli.egg-info/top_level.txt