Metadata-Version: 2.1
Name: wut-cli
Version: 1.0.6
Summary: CLI that explains the output of your last command
Home-page: https://github.com/shobrook/wut
Author: shobrook
Author-email: shobrookj@gmail.com
License: MIT
Keywords: openai claude cli commandline error stack-trace explain assistant terminal
Classifier: Environment :: Console
Classifier: Intended Audience :: Developers
Classifier: Topic :: Software Development
Classifier: Topic :: Software Development :: Debuggers
Classifier: Natural Language :: English
Classifier: License :: OSI Approved :: MIT License
Classifier: Programming Language :: Python
Requires: openai
Requires: anthropic
Requires: ollama
Requires: rich
Requires: psutil
Requires-Python: >=3
License-File: LICENSE
Requires-Dist: openai
Requires-Dist: anthropic
Requires-Dist: ollama
Requires-Dist: rich
Requires-Dist: psutil
